systemstoolkit/__init__.py
systemstoolkit/typing.py
systemstoolkit/utils.py
systemstoolkit/files/__init__.py
systemstoolkit/files/builders.py
systemstoolkit/files/files.py
systemstoolkit/files/formats.py
systemstoolkit/files/keywords.py
systemstoolkit/files/validators.py
systemstoolkit/units/__init__.py
systemstoolkit/units/time.py
systemstoolkit-0.0.2.dist-info/LICENSE
systemstoolkit-0.0.2.dist-info/METADATA
systemstoolkit-0.0.2.dist-info/WHEEL
systemstoolkit-0.0.2.dist-info/top_level.txt
systemstoolkit-0.0.2.dist-info/RECORD
