Metadata-Version: 2.1
Name: systemstoolkit
Version: 0.0.2
Summary: Helper functions for Systems ToolKit (STK)
License: MIT License
Project-URL: Homepage, https://github.com/jolsten/systemstoolkit
Classifier: License :: OSI Approved :: MIT License
Classifier: Programming Language :: Python :: 3
Classifier: Programming Language :: Python :: 3.8
Requires-Python: >=3.8
License-File: LICENSE
Requires-Dist: numpy
Requires-Dist: dateutils
